sprawl/__init__.py
sprawl/cell.py
sprawl/command_line.py
sprawl/hdf5.py
sprawl/metrics.py
sprawl/plotting.py
sprawl/scoring.py
sprawl/simulate.py
sprawl/utils.py
sprawl/vignette.py
sprawl/vignette_data/CB_XO_mapping.csv
sprawl/vignette_data/__init__.py
sprawl/vignette_data/merfish_m1s4_vignette.hdf5
sprawl/vignette_data/merfish_m2s4_vignette.hdf5
sprawl/vignette_data/no_ont.bam
sprawl/vignette_data/no_ont.bam.bai
sprawl/vignette_data/no_var_merfish_m1s4_vignette.hdf5
sprawl/vignette_data/no_var_merfish_m2s4_vignette.hdf5
sprawl/vignette_data/ont_ann.bam
sprawl/vignette_data/ont_ann.bam.bai
sprawl/vignette_data/sim_radial_cell.hdf5
sprawl/vignette_data/timp3.bam
sprawl/vignette_data/timp3.bam.bai
sprawl/vignette_data/timp3.gtf
sprawl/vignette_data/timp3_peripheral.csv
sprawl/vignette_data/__pycache__/__init__.cpython-36.pyc
sprawl/vignette_data/__pycache__/__init__.cpython-38.pyc
sprawl/vignette_data/__pycache__/__init__.cpython-39.pyc
subcellular_sprawl-0.5.dist-info/METADATA
subcellular_sprawl-0.5.dist-info/WHEEL
subcellular_sprawl-0.5.dist-info/entry_points.txt
subcellular_sprawl-0.5.dist-info/top_level.txt
subcellular_sprawl-0.5.dist-info/RECORD
